<?xml version="1.0"?>
<trik>

    <about>
			<nazev>Falešné mills' mess</nazev>
		 <pocet>3</pocet>
	     <siteswaps>-</siteswaps>
		 <obtiznost>náročné</obtiznost>
		 <oblast>micky-3</oblast>
	</about>

	<krok>
		<popisek>Popsat tento trik je skoro stejně těžké jako se ho naučit. Takže hurá do toho!</popisek>
	</krok>

    <krok>
			<obrazek>micky-3-mm-falesnea</obrazek>
			<popisek>Ruce jsou překřížené, pravá nad levou. Vyhoď první míček z pravé ruky. Ihned po vyhození si ruce vyměňují místo.</popisek>
    </krok>


    <krok>
			<obrazek>micky-3-mm-falesneb</obrazek>
			<popisek>Ruce jsou nepřekřížené. Vyhoď druhý míček z levé ruky rovně nahoru. Ruce si opět vyměňují pozice.</popisek>
    </krok>


    <krok>
			<obrazek>micky-3-mm-falesnec</obrazek>
			<popisek>Do levé ruky zachytíš první míček a hodíš ho zpět. Oproti &lt;a href=&quot;mm.html&quot; title=&quot;Mills' mess v plné kráse.&quot;&gt;úplnému mills' mess&lt;/a&gt; třetí míček zůstává v pravé ruce.</popisek>
    </krok>


    <krok>
			<obrazek>micky-3-mm-falesned</obrazek>
			<popisek>Následuje překřížení rukou. Levá ruka chytí druhý míček.</popisek>
    </krok>


    <krok>
			<obrazek>micky-3-mm-falesnee</obrazek>
			<popisek>Z pravé ruky vyhodíš rovně nahoru třetí míček. Zároveň ruce překřížíš, aby pravá ruka mohla chytit první míček.</popisek>
    </krok>


    <krok>
			<obrazek>micky-3-mm-falesnef</obrazek>
			<popisek>První míček hodíš z pravé ruky zpět. Druhý míček zůstává v levé ruce.</popisek>
    </krok>


</trik>
